tests/__init__.py
tests/test_create_wacz.py
tests/test_create_wacz_hash_in_page.py
tests/test_create_wacz_indexing.py
tests/test_optional_flags_wacz.py
tests/test_util.py
tests/test_validate_wacz.py
tests/test_verify_signed.py
tests/test_wacz_indexer_functions.py
wacz/__init__.py
wacz/__main__.py
wacz/main.py
wacz/util.py
wacz/validate.py
wacz/waczindexer.py
wacz-0.5.0.dist-info/LICENSE
wacz-0.5.0.dist-info/METADATA
wacz-0.5.0.dist-info/WHEEL
wacz-0.5.0.dist-info/entry_points.txt
wacz-0.5.0.dist-info/top_level.txt
wacz-0.5.0.dist-info/zip-safe
wacz-0.5.0.dist-info/RECORD
