Metadata-Version: 2.1
Name: wacz
Version: 0.5.0
Summary: WACZ Format Tools
Home-page: https://github.com/webrecorder/py-wacz
Author: Ilya Kreymer, Emma Dickson
Author-email: info@webrecorder.net
License: Apache 2.0
Platform: UNKNOWN
License-File: LICENSE
Requires-Dist: frictionless >=3.23.4
Requires-Dist: shortuuid >=1.0.1
Requires-Dist: cdxj-indexer >=1.4.4
Requires-Dist: boilerpy3 >=1.0.2
Requires-Dist: pytest-cov >=2.10.1
Requires-Dist: PyYAML >=5.3.1
Requires-Dist: black >=20.8b1
Requires-Dist: jsonlines >=3.0.0
Requires-Dist: click >=8.0.0
Requires-Dist: typer ==0.11.1
Provides-Extra: signing
Requires-Dist: authsign >=0.5.1 ; extra == 'signing'
Requires-Dist: requests ; extra == 'signing'
